setup.py
swabberd
swabber/__init__.py
swabber/bancleaner.py
swabber/banfetcher.py
swabber/banobjects.py
swabber/hostsfile.py
swabber/testing.py
swabber.egg-info/PKG-INFO
swabber.egg-info/SOURCES.txt
swabber.egg-info/dependency_links.txt
swabber.egg-info/requires.txt
swabber.egg-info/top_level.txt