Metadata-Version: 1.1
Name: swabber
Version: 1.3.4
Summary: Pubsub-based host banning interface
Home-page: http://github.com/equalitie/swabber
Author: Hugh Nowlan
Author-email: nosmo@nosmo.me
License: N(C)
Keywords: iptables banning pubsub
Platform: UNKNOWN
Classifier: Development Status :: 5 - Production/Stable
Classifier: Topic :: Security
Classifier: Intended Audience :: System Administrators
